potent/__init__.py
potent/cli.py
potent/commands/_types.py
potent/commands/init.py
potent/commands/reset.py
potent/commands/run.py
potent/commands/summarize.py
potent/operations/_base.py
potent/operations/create_pr.py
potent/operations/enable_automerge.py
potent/operations/git_add.py
potent/operations/git_commit.py
potent/operations/git_pull.py
potent/operations/git_push.py
potent/operations/git_status.py
potent/operations/git_switch.py
potent/operations/raw_command.py
potent/plan.py
potent/util.py
potent-0.2.2.dist-info/licenses/LICENSE
potent-0.2.2.dist-info/WHEEL
potent-0.2.2.dist-info/entry_points.txt
potent-0.2.2.dist-info/METADATA
potent-0.2.2.dist-info/RECORD
