Metadata-Version: 2.4
Name: potent
Version: 0.2.2
Summary: An idempotent way to run shell scripts.
Keywords: automation,shell-scripting,idempotency,CLI tool
Author: David Brownman
Author-email: David Brownman <oss@xavd.id>
License-File: LICENSE
Classifier: Development Status :: 4 - Beta
Classifier: Programming Language :: Python :: 3 :: Only
Classifier: Programming Language :: Python :: 3.12
Classifier: Programming Language :: Python :: 3.13
Classifier: Programming Language :: Python :: 3.14
Classifier: Topic :: Software Development
Classifier: Topic :: System :: Shells
Classifier: Topic :: Utilities
Requires-Dist: pydantic~=2.12
Requires-Dist: rich
Requires-Dist: typer==0.20.0
Requires-Python: >=3.12
Project-URL: Changelog, https://github.com/xavdid/potent/blob/main/CHANGELOG.md
Project-URL: Issues, https://github.com/xavdid/potent/issues
Project-URL: Repository, https://github.com/xavdid/potent
